piretry/__init__.py
piretry/decorators.py
piretry-0.1.2.dist-info/LICENSE
piretry-0.1.2.dist-info/METADATA
piretry-0.1.2.dist-info/WHEEL
piretry-0.1.2.dist-info/top_level.txt
piretry-0.1.2.dist-info/RECORD
