Metadata-Version: 2.2
Name: piretry
Version: 0.1.2
Summary: A decorator to retry a function if it raises an exception
Home-page: https://github.com/APTIVMIND/piretry
Author: APTIVMIND
Author-email: aptivmind@gmail.com
Requires-Python: >=3.12
License-File: LICENSE
Requires-Dist: setuptools>=75.8.0
Requires-Dist: twine>=6.1.0
Requires-Dist: wheel>=0.45.1
Dynamic: author
Dynamic: author-email
Dynamic: home-page
Dynamic: requires-python
